{
  "age": "22 years, 2 months, 13 days",
  "os": "Windows 11, Ubuntu",
  "host": "OMEN 15",
  "kernel": "Fullstack Dev, Backend, AL/ML",
  "ide": "VScode, Clion, Arduino IDE",
  "edu": "Computer Engineering Student @ POLINES",
  "languages_programming": "Python, JS, TS, C/C++, PHP, Java, SQL",
  "languages_real": "English, Indonesian",
  "hobbies_software": "AI Project, Web Dev, Discord Bot",
  "hobbies_life": "Powerlifting, Gaming, Coffee",
  "portfolio": "zulvikar.is-a.dev/",
  "email": "zulvikar.kharisma22@gmail.com",
  "linkedin": "in/zulvikar-kharisma",
  "discord": "dycandx",
  "repos": 39,
  "stars": 24,
  "commits": 764,
  "followers": 3,
  "contributions": 42,
  "loc_add": "5,339,384",
  "loc_del": "3,996,153",
  "loc_total": "1,343,231"
}